osxlaunch/__init__.py
osxlaunch/__main__.py
osxlaunch/version.py
osxlaunch-0.1.2.dist-info/DESCRIPTION.rst
osxlaunch-0.1.2.dist-info/METADATA
osxlaunch-0.1.2.dist-info/RECORD
osxlaunch-0.1.2.dist-info/WHEEL
osxlaunch-0.1.2.dist-info/entry_points.txt
osxlaunch-0.1.2.dist-info/metadata.json
osxlaunch-0.1.2.dist-info/top_level.txt
