Metadata-Version: 2.0
Name: osxlaunch
Version: 0.1.2
Summary: Utility for working with OSX launchd environment variables.
Home-page: https://github.com/zzzirk/osxlaunch
Author: Louis Zirkel III
Author-email: zzzirk@gmail.com
License: BSD License
Keywords: osx macos plist launchd launchctl environment environ
Platform: UNKNOWN
Classifier: Development Status :: 3 - Alpha
Classifier: Environment :: Console
Classifier: Intended Audience :: Developers
Classifier: License :: OSI Approved :: BSD License
Classifier: Operating System :: MacOS :: MacOS X
Classifier: Programming Language :: Python
Classifier: Programming Language :: Python :: 2
Classifier: Programming Language :: Python :: 2.7
Classifier: Programming Language :: Python :: 3
Classifier: Programming Language :: Python :: 3.3
Classifier: Programming Language :: Python :: 3.4
Classifier: Programming Language :: Python :: 3.5
Classifier: Programming Language :: Python :: 3.6
Classifier: Topic :: System :: Installation/Setup
Classifier: Topic :: Utilities
